pm/tsession/__about__.py
pm/tsession/__init__.py
pm/tsession/__main__.py
pm_tsession-0.0.3.dist-info/METADATA
pm_tsession-0.0.3.dist-info/WHEEL
pm_tsession-0.0.3.dist-info/entry_points.txt
pm_tsession-0.0.3.dist-info/licenses/LICENSE.txt
pm_tsession-0.0.3.dist-info/RECORD
