Metadata-Version: 2.1
Name: pm-tsession
Version: 0.0.3
Summary: Paste text into tmux windows and capture output
Project-URL: Documentation, https://github.com/unknown/pm-tsession#readme
Project-URL: Issues, https://github.com/unknown/pm-tsession/issues
Project-URL: Source, https://github.com/unknown/pm-tsession
Author-email: Trey Hunner <trey@treyhunner.com>
License-Expression: MIT
License-File: LICENSE.txt
Classifier: Development Status :: 4 - Beta
Classifier: Programming Language :: Python
Classifier: Programming Language :: Python :: 3.8
Classifier: Programming Language :: Python :: 3.9
Classifier: Programming Language :: Python :: 3.10
Classifier: Programming Language :: Python :: 3.11
Classifier: Programming Language :: Python :: 3.12
Classifier: Programming Language :: Python :: Implementation :: CPython
Classifier: Programming Language :: Python :: Implementation :: PyPy
Requires-Python: >=3.8
Requires-Dist: libtmux==0.20.0
